neon_tts_plugin_mimic/__init__.py
neon_tts_plugin_mimic-0.1.8.dist-info/METADATA
neon_tts_plugin_mimic-0.1.8.dist-info/WHEEL
neon_tts_plugin_mimic-0.1.8.dist-info/entry_points.txt
neon_tts_plugin_mimic-0.1.8.dist-info/top_level.txt
neon_tts_plugin_mimic-0.1.8.dist-info/zip-safe
neon_tts_plugin_mimic-0.1.8.dist-info/RECORD
