Metadata-Version: 2.1
Name: neon-tts-plugin-mimic
Version: 0.1.8
Summary: mimic tts plugin for NeonCore
Home-page: https://github.com/NeonGeckoCom/neon-tts-plugin-mimic
Author: NeonGecko
Author-email: developers@neon.ai
License: Apache-2.0
Keywords: neon mycroft plugin tts OVOS OpenVoiceOS
Platform: UNKNOWN
Classifier: Development Status :: 3 - Alpha
Classifier: Intended Audience :: Developers
Classifier: Topic :: Text Processing :: Linguistic
Classifier: License :: OSI Approved :: Apache Software License
Classifier: Programming Language :: Python :: 2
Classifier: Programming Language :: Python :: 2.7
Classifier: Programming Language :: Python :: 3
Classifier: Programming Language :: Python :: 3.0
Classifier: Programming Language :: Python :: 3.1
Classifier: Programming Language :: Python :: 3.2
Classifier: Programming Language :: Python :: 3.3
Classifier: Programming Language :: Python :: 3.4
Classifier: Programming Language :: Python :: 3.5
Classifier: Programming Language :: Python :: 3.6
Requires-Dist: ovos-plugin-manager (~=0.0.16)
Requires-Dist: ovos-utils (~=0.0.15)
